pyscan_tlk/__init__.py
pyscan_tlk/benchtopbrushlessmotor.py
pyscan_tlk/benchtopdcservo.py
pyscan_tlk/benchtopnanotrack.py
pyscan_tlk/benchtoppiezo.py
pyscan_tlk/benchtoppiezopdxc2.py
pyscan_tlk/benchtopprecisionpiezo.py
pyscan_tlk/benchtopsteppermotor.py
pyscan_tlk/benchtopvoicecoil.py
pyscan_tlk/filterflipper.py
pyscan_tlk/integratedprecisionpiezo.py
pyscan_tlk/integratedsteppermotor.py
pyscan_tlk/kcubebrushlessmotor.py
pyscan_tlk/kcubedcservo.py
pyscan_tlk/kcubeinertialmotor.py
pyscan_tlk/kcubelaserdiode.py
pyscan_tlk/kcubelasersource.py
pyscan_tlk/kcubenanotrack.py
pyscan_tlk/kcubepiezo.py
pyscan_tlk/kcubepiezostraingauge.py
pyscan_tlk/kcubepositionaligner.py
pyscan_tlk/kcubesolenoid.py
pyscan_tlk/kcubesteppermotor.py
pyscan_tlk/modularnanotrack.py
pyscan_tlk/modularsteppermotor.py
pyscan_tlk/polarizer.py
pyscan_tlk/tcubebrushlessmotor.py
pyscan_tlk/tcubeinertialmotor.py
pyscan_tlk/tcubelaserdiode.py
pyscan_tlk/tcubelasersource.py
pyscan_tlk/tcubenanotrack.py
pyscan_tlk/tcubepiezo.py
pyscan_tlk/tcubequad.py
pyscan_tlk/tcubeservo.py
pyscan_tlk/tcubesolenoid.py
pyscan_tlk/tcubesteppermotor.py
pyscan_tlk/tcubestraingauge.py
pyscan_tlk/tcubetec.py
pyscan_tlk/version.json
pyscan_tlk/definitions/__init__.py
pyscan_tlk/definitions/enumeration.py
pyscan_tlk/definitions/enumerations.py
pyscan_tlk/definitions/kinesisexception.py
pyscan_tlk/definitions/safearray.py
pyscan_tlk/definitions/structures.py
pyscan_tlk-0.1.9.dist-info/LICENSE
pyscan_tlk-0.1.9.dist-info/METADATA
pyscan_tlk-0.1.9.dist-info/WHEEL
pyscan_tlk-0.1.9.dist-info/top_level.txt
pyscan_tlk-0.1.9.dist-info/RECORD
