Metadata-Version: 2.1
Name: pyscan_tlk
Version: 0.1.9
Summary: Thorlabs Kinesis python wrappers
Author-email: Andy Mounce <ammounce@gmail.com>
License: MIT License
Keywords: thorlabs,kinesis,instrument control,science
Requires-Python: >=3.7
License-File: LICENSE
Requires-Dist: comtypes
